Plant-Nanny-DB/__init__.py
Plant-Nanny-DB/__main__.py
Plant-Nanny-DB/dictionaries.py
Plant-Nanny-DB/logger.py
Plant-Nanny-DB/settings.py
PlantNannyDB/__init__.py
PlantNannyDB/__main__.py
PlantNannyDB/database_use.py
PlantNannyDB/dictionaries.py
PlantNannyDB/logger.py
PlantNannyDB/settings.py
PlantNannyDB-1.4.6.dist-info/LICENSE.txt
PlantNannyDB-1.4.6.dist-info/METADATA
PlantNannyDB-1.4.6.dist-info/WHEEL
PlantNannyDB-1.4.6.dist-info/top_level.txt
PlantNannyDB-1.4.6.dist-info/RECORD
