Metadata-Version: 2.1
Name: PlantNannyDB
Version: 1.4.6
Summary: Enable read/write functionality for Plant Nanny Database
Home-page: https://github.com/loganbalkwill/plant-nanny-db
Author: Logan Balkwill
Author-email: lgb0020@gmail.com
License: MIT
Platform: UNKNOWN
Requires-Dist: importlib
Requires-Dist: mysqlclient
